norma/__init__.py
norma/cli.py
norma/exceptions.py
norma/adapters/__init__.py
norma/adapters/base_adapter.py
norma/adapters/cassandra_adapter.py
norma/adapters/mongo_adapter.py
norma/adapters/sql_adapter.py
norma/core/__init__.py
norma/core/base_model.py
norma/core/client.py
norma/core/field.py
norma/core/relationship_manager.py
norma/migrations/__init__.py
norma/migrations/migration_manager.py
norma/performance/__init__.py
norma/performance/query_optimizer.py
norma/schema/__init__.py
norma/schema/generator.py
norma_orm-0.1.1.dist-info/licenses/LICENSE
norma_orm-0.1.1.dist-info/METADATA
norma_orm-0.1.1.dist-info/WHEEL
norma_orm-0.1.1.dist-info/entry_points.txt
norma_orm-0.1.1.dist-info/top_level.txt
norma_orm-0.1.1.dist-info/RECORD
