Metadata-Version: 2.4
Name: norma-orm
Version: 0.1.1
Summary: A modern Python ORM framework with dataclass support
Home-page: https://github.com/Geoion/Norma
Author: Geoion
Author-email: Geoion <eski.yin@gmail.com>
License-Expression: MIT
Project-URL: Homepage, https://github.com/Geoion/Norma
Project-URL: Documentation, https://github.com/Geoion/Norma
Project-URL: Repository, https://github.com/Geoion/Norma.git
Project-URL: Bug Tracker, https://github.com/Geoion/Norma/issues
Keywords: orm,database,dataclass,pydantic,postgresql,sqlite,mongodb,cassandra,CLI,flask,fastapi
Classifier: Development Status :: 3 - Alpha
Classifier: Intended Audience :: Developers
Classifier: Operating System :: OS Independent
Classifier: Programming Language :: Python :: 3
Classifier: Programming Language :: Python :: 3.8
Classifier: Programming Language :: Python :: 3.9
Classifier: Programming Language :: Python :: 3.10
Classifier: Programming Language :: Python :: 3.11
Classifier: Programming Language :: Python :: 3.12
Classifier: Topic :: Database
Classifier: Topic :: Software Development :: Libraries :: Python Modules
Classifier: Typing :: Typed
Requires-Python: >=3.8
License-File: LICENSE
Requires-Dist: pydantic>=2.0.0
Requires-Dist: typer>=0.9.0
Requires-Dist: sqlalchemy>=2.0.0
Requires-Dist: motor>=3.0.0
Requires-Dist: pymongo>=4.0.0
Requires-Dist: asyncpg>=0.28.0
Requires-Dist: aiosqlite>=0.19.0
Provides-Extra: dev
Requires-Dist: pytest>=7.0.0; extra == "dev"
Requires-Dist: pytest-asyncio>=0.21.0; extra == "dev"
Requires-Dist: black>=23.0.0; extra == "dev"
Requires-Dist: isort>=5.12.0; extra == "dev"
Requires-Dist: mypy>=1.0.0; extra == "dev"
Requires-Dist: rich>=13.0.0; extra == "dev"
Requires-Dist: watchdog>=3.0.0; extra == "dev"
Provides-Extra: postgres
Requires-Dist: psycopg2-binary>=2.9.0; extra == "postgres"
Provides-Extra: mysql
Requires-Dist: pymysql>=1.0.0; extra == "mysql"
Provides-Extra: cassandra
Requires-Dist: cassandra-driver>=3.25.0; extra == "cassandra"
Provides-Extra: cli
Requires-Dist: rich>=13.0.0; extra == "cli"
Dynamic: author
Dynamic: home-page
Dynamic: license-file
Dynamic: requires-python
